<?xml version="1.0" encoding="UTF-8"?>
<MetaDataObject xmlns="http://v8.1c.ru/8.3/MDClasses" xmlns:app="http://v8.1c.ru/8.2/managed-application/core" xmlns:cfg="http://v8.1c.ru/8.1/data/enterprise/current-config" xmlns:cmi="http://v8.1c.ru/8.2/managed-application/cmi" xmlns:ent="http://v8.1c.ru/8.1/data/enterprise" xmlns:lf="http://v8.1c.ru/8.2/managed-application/logform" xmlns:style="http://v8.1c.ru/8.1/data/ui/style" xmlns:sys="http://v8.1c.ru/8.1/data/ui/fonts/system" xmlns:v8="http://v8.1c.ru/8.1/data/core" xmlns:v8ui="http://v8.1c.ru/8.1/data/ui" xmlns:web="http://v8.1c.ru/8.1/data/ui/colors/web" xmlns:win="http://v8.1c.ru/8.1/data/ui/colors/windows" xmlns:xen="http://v8.1c.ru/8.3/xcf/enums" xmlns:xpr="http://v8.1c.ru/8.3/xcf/predef" xmlns:xr="http://v8.1c.ru/8.3/xcf/readable" xmlns:xs="http://www.w3.org/2001/XMLSchema" xmlns:xsi="http://www.w3.org/2001/XMLSchema-instance" version="2.9">
	<Constant uuid="a8d54e92-7f03-44c1-bbff-dae8fd0c5165">
		<InternalInfo>
			<xr:GeneratedType name="ConstantManager.ВестиРаздельнуюНумерациюНалоговыхДокументов" category="Manager">
				<xr:TypeId>642e6068-e955-477b-a5e9-e60f6317ac75</xr:TypeId>
				<xr:ValueId>7d1ecb24-301a-4b95-b7e8-9766661d5958</xr:ValueId>
			</xr:GeneratedType>
			<xr:GeneratedType name="ConstantValueManager.ВестиРаздельнуюНумерациюНалоговыхДокументов" category="ValueManager">
				<xr:TypeId>565fcbe7-c0ba-4867-ade3-ca8611acb587</xr:TypeId>
				<xr:ValueId>df1e3dec-a174-4957-be3e-f16c56d6c570</xr:ValueId>
			</xr:GeneratedType>
			<xr:GeneratedType name="ConstantValueKey.ВестиРаздельнуюНумерациюНалоговыхДокументов" category="ValueKey">
				<xr:TypeId>7765f3ae-2976-53a0-8036-6b1a73c91451</xr:TypeId>
				<xr:ValueId>39c56600-a7e3-56f5-9cdb-d5997fc1d436</xr:ValueId>
			</xr:GeneratedType>
		</InternalInfo>
		<Properties>
			<Name>ВестиРаздельнуюНумерациюНалоговыхДокументов</Name>
			<Synonym>
				<v8:item>
					<v8:lang>ru</v8:lang>
					<v8:content>Вести раздельную нумерацию налоговых документов</v8:content>
				</v8:item>
				<v8:item>
					<v8:lang>uk</v8:lang>
					<v8:content>Вести роздільну нумерацію податкових документів</v8:content>
				</v8:item>
			</Synonym>
			<Comment>Разные нумераторы для Налоговой накладной и Приложения 2 к налоговой накладной</Comment>
			<Type>
				<v8:Type>xs:boolean</v8:Type>
			</Type>
			<UseStandardCommands>true</UseStandardCommands>
			<DefaultForm/>
			<ExtendedPresentation/>
			<Explanation/>
			<PasswordMode>false</PasswordMode>
			<Format/>
			<EditFormat/>
			<ToolTip/>
			<MarkNegatives>false</MarkNegatives>
			<Mask/>
			<MultiLine>false</MultiLine>
			<ExtendedEdit>false</ExtendedEdit>
			<MinValue xsi:nil="true"/>
			<MaxValue xsi:nil="true"/>
			<FillChecking>DontCheck</FillChecking>
			<ChoiceFoldersAndItems>Items</ChoiceFoldersAndItems>
			<ChoiceParameterLinks/>
			<ChoiceParameters/>
			<QuickChoice>Auto</QuickChoice>
			<ChoiceForm/>
			<LinkByType/>
			<ChoiceHistoryOnInput>Auto</ChoiceHistoryOnInput>
			<DataLockControlMode>Managed</DataLockControlMode>
			<DataHistory>DontUse</DataHistory>
			<UpdateDataHistoryImmediatelyAfterWrite>false</UpdateDataHistoryImmediatelyAfterWrite>
			<ExecuteAfterWriteDataHistoryVersionProcessing>false</ExecuteAfterWriteDataHistoryVersionProcessing>
		</Properties>
	</Constant>
</MetaDataObject>